qiskit_superstaq/__init__.py
qiskit_superstaq/_version.py
qiskit_superstaq/_version_test.py
qiskit_superstaq/compiler_output.py
qiskit_superstaq/compiler_output_test.py
qiskit_superstaq/conftest.py
qiskit_superstaq/custom_gates.py
qiskit_superstaq/custom_gates_test.py
qiskit_superstaq/daily_integration_test.py
qiskit_superstaq/py.typed
qiskit_superstaq/serialization.py
qiskit_superstaq/serialization_test.py
qiskit_superstaq/superstaq_backend.py
qiskit_superstaq/superstaq_backend_test.py
qiskit_superstaq/superstaq_job.py
qiskit_superstaq/superstaq_job_test.py
qiskit_superstaq/superstaq_provider.py
qiskit_superstaq/superstaq_provider_test.py
qiskit_superstaq/validation.py
qiskit_superstaq/validation_test.py
qiskit_superstaq-0.5.61.dist-info/METADATA
qiskit_superstaq-0.5.61.dist-info/WHEEL
qiskit_superstaq-0.5.61.dist-info/top_level.txt
qiskit_superstaq-0.5.61.dist-info/RECORD
