Metadata-Version: 2.4
Name: qiskit-superstaq
Version: 0.5.61
Summary: The Qiskit module that provides tools and access to Superstaq.
Author-email: Superstaq development team <superstaq@infleqtion.com>
License: Apache-2.0
Project-URL: homepage, https://github.com/Infleqtion/client-superstaq
Requires-Python: >=3.9.0
Requires-Dist: general-superstaq~=0.5.61
Requires-Dist: qiskit>=1.3.0; python_version < "3.14"
Requires-Dist: qiskit>=2.1.0; python_version >= "3.14"
Requires-Dist: symengine~=0.13.0; python_version < "3.14"
Provides-Extra: dev
Requires-Dist: checks-superstaq~=0.5.61; extra == "dev"
Provides-Extra: examples
Requires-Dist: matplotlib>=3.7.0; extra == "examples"
Requires-Dist: notebook>=6.5.5; extra == "examples"
Requires-Dist: pylatexenc>=2.0; extra == "examples"
